llemon/__init__.py
llemon/apis/__init__.py
llemon/apis/llm/__init__.py
llemon/apis/llm/llm.py
llemon/apis/llm/llm_model.py
llemon/apis/llm/llm_model_config.py
llemon/apis/llm/llm_model_property.py
llemon/apis/stt/__init__.py
llemon/apis/tts/__init__.py
llemon/conversation.py
llemon/errors.py
llemon/models/__init__.py
llemon/models/file.py
llemon/models/generate.py
llemon/models/generate_data.py
llemon/models/generate_stream.py
llemon/models/history.py
llemon/models/request.py
llemon/models/tool.py
llemon/providers/__init__.py
llemon/providers/anthropic.py
llemon/providers/deepinfra.py
llemon/providers/gemini.py
llemon/providers/openai.py
llemon/tools/__init__.py
llemon/tools/database.py
llemon/tools/directory.py
llemon/tools/toolbox.py
llemon/types.py
llemon/utils/__init__.py
llemon/utils/concat.py
llemon/utils/formatting.py
llemon/utils/logs.py
llemon/utils/now.py
llemon/utils/parallelize.py
llemon/utils/schema.py
llemon/utils/trim.py
llemon-0.2.0.dist-info/METADATA
llemon-0.2.0.dist-info/WHEEL
llemon-0.2.0.dist-info/RECORD
