Metadata-Version: 2.3
Name: llemon
Version: 0.2.0
Summary: 
Author: Dan Gittik
Author-email: dan.gittik@gmail.com
Requires-Python: >=3.12
Classifier: Programming Language :: Python :: 3
Classifier: Programming Language :: Python :: 3.12
Classifier: Programming Language :: Python :: 3.13
Requires-Dist: anthropic (>=0.60.0,<0.61.0)
Requires-Dist: dotenv (>=0.9.9,<0.10.0)
Requires-Dist: google-genai (>=1.28.0,<2.0.0)
Requires-Dist: jinja2 (>=3.1.6,<4.0.0)
Requires-Dist: openai (>=1.98.0,<2.0.0)
Requires-Dist: pydantic (>=2.11.7,<3.0.0)
Requires-Dist: rich (>=14.1.0,<15.0.0)
Requires-Dist: sqlalchemy (>=2.0.43,<3.0.0)
